{
  "_class": "group",
  "do_objectID": "F3325EF7-B736-4694-B4EC-A49C19CC3524",
  "exportOptions": {
    "_class": "exportOptions",
    "exportFormats": [
    ],
    "includedLayerIds": [
    ],
    "layerOptions": 0,
    "shouldTrim": false
  },
  "frame": {
    "_class": "rect",
    "constrainProportions": false,
    "height": 111,
    "width": 80,
    "x": 601,
    "y": 358
  },
  "hasClickThrough": false,
  "isFlippedHorizontal": false,
  "isFlippedVertical": false,
  "isLocked": false,
  "isVisible": true,
  "layerListExpandedType": 0,
  "layers": [
    {
      "class": "symbolInstance",
      "id": "0A1BB891-3CBE-4A65-8263-D7CFF1CA3149"
    },
    {
      "class": "text",
      "id": "0EED4F27-E3D6-41BC-A222-8086C274D639"
    }
  ],
  "name": "User 2",
  "nameIsFixed": true,
  "resizingConstraint": 61,
  "resizingType": 0,
  "rotation": 0,
  "shouldBreakMaskChain": false,
  "style": {
    "_class": "style",
    "endDecorationType": 0,
    "miterLimit": 10,
    "startDecorationType": 0
  }
}