{
  "_class": "shapePath",
  "booleanOperation": 0,
  "do_objectID": "F1369865-1362-4AF6-BF10-2E34BF151788",
  "edited": true,
  "exportOptions": {
    "_class": "exportOptions",
    "exportFormats": [
    ],
    "includedLayerIds": [
    ],
    "layerOptions": 0,
    "shouldTrim": false
  },
  "frame": {
    "_class": "rect",
    "constrainProportions": false,
    "height": 7.289553366604444,
    "width": 2.454432477216264,
    "x": 15.54556752278374,
    "y": 6.322827035493402
  },
  "isClosed": false,
  "isFlippedHorizontal": false,
  "isFlippedVertical": false,
  "isLocked": false,
  "isVisible": true,
  "layerListExpandedType": 0,
  "name": "Fill 242",
  "nameIsFixed": false,
  "path": {
    "_class": "path",
    "isClosed": false,
    "pointRadiusBehaviour": 0,
    "points": [
      {
        "_class": "curvePoint",
        "cornerRadius": 0,
        "curveFrom": "{0.22379746835443148, 0}",
        "curveMode": 4,
        "curveTo": "{0.50025316455692725, 0}",
        "hasCurveFrom": true,
        "hasCurveTo": false,
        "point": "{0.50025316455692725, 0}"
      },
      {
        "_class": "curvePoint",
        "cornerRadius": 0,
        "curveFrom": "{0, 0.15921922890789181}",
        "curveMode": 4,
        "curveTo": "{0, 0.071301822874658236}",
        "hasCurveFrom": false,
        "hasCurveTo": true,
        "point": "{0, 0.15921922890789181}"
      },
      {
        "_class": "curvePoint",
        "cornerRadius": 0,
        "curveFrom": "{0, 0.92869817712534175}",
        "curveMode": 4,
        "curveTo": "{0, 0.84078077109211735}",
        "hasCurveFrom": true,
        "hasCurveTo": false,
        "point": "{0, 0.84078077109211735}"
      },
      {
        "_class": "curvePoint",
        "cornerRadius": 0,
        "curveFrom": "{0.77620253164556852, 1}",
        "curveMode": 2,
        "curveTo": "{0.22379746835443148, 1}",
        "hasCurveFrom": true,
        "hasCurveTo": true,
        "point": "{0.50025316455692725, 1}"
      },
      {
        "_class": "curvePoint",
        "cornerRadius": 0,
        "curveFrom": "{1, 0.84078077109211735}",
        "curveMode": 4,
        "curveTo": "{1, 0.92869817712534175}",
        "hasCurveFrom": false,
        "hasCurveTo": true,
        "point": "{1, 0.84078077109211735}"
      },
      {
        "_class": "curvePoint",
        "cornerRadius": 0,
        "curveFrom": "{1, 0.071301822874658236}",
        "curveMode": 4,
        "curveTo": "{1, 0.15921922890789181}",
        "hasCurveFrom": true,
        "hasCurveTo": false,
        "point": "{1, 0.15921922890789181}"
      },
      {
        "_class": "curvePoint",
        "cornerRadius": 0,
        "curveFrom": "{0.50025316455692725, 0}",
        "curveMode": 4,
        "curveTo": "{0.77620253164556852, 0}",
        "hasCurveFrom": false,
        "hasCurveTo": true,
        "point": "{0.50025316455692725, 0}"
      }
    ]
  },
  "pointRadiusBehaviour": 0,
  "points": [
    {
      "_class": "curvePoint",
      "cornerRadius": 0,
      "curveFrom": "{0.22379746835443148, 0}",
      "curveMode": 4,
      "curveTo": "{0.50025316455692725, 0}",
      "hasCurveFrom": true,
      "hasCurveTo": false,
      "point": "{0.50025316455692725, 0}"
    },
    {
      "_class": "curvePoint",
      "cornerRadius": 0,
      "curveFrom": "{0, 0.15921922890789181}",
      "curveMode": 4,
      "curveTo": "{0, 0.071301822874658236}",
      "hasCurveFrom": false,
      "hasCurveTo": true,
      "point": "{0, 0.15921922890789181}"
    },
    {
      "_class": "curvePoint",
      "cornerRadius": 0,
      "curveFrom": "{0, 0.92869817712534175}",
      "curveMode": 4,
      "curveTo": "{0, 0.84078077109211735}",
      "hasCurveFrom": true,
      "hasCurveTo": false,
      "point": "{0, 0.84078077109211735}"
    },
    {
      "_class": "curvePoint",
      "cornerRadius": 0,
      "curveFrom": "{0.77620253164556852, 1}",
      "curveMode": 2,
      "curveTo": "{0.22379746835443148, 1}",
      "hasCurveFrom": true,
      "hasCurveTo": true,
      "point": "{0.50025316455692725, 1}"
    },
    {
      "_class": "curvePoint",
      "cornerRadius": 0,
      "curveFrom": "{1, 0.84078077109211735}",
      "curveMode": 4,
      "curveTo": "{1, 0.92869817712534175}",
      "hasCurveFrom": false,
      "hasCurveTo": true,
      "point": "{1, 0.84078077109211735}"
    },
    {
      "_class": "curvePoint",
      "cornerRadius": 0,
      "curveFrom": "{1, 0.071301822874658236}",
      "curveMode": 4,
      "curveTo": "{1, 0.15921922890789181}",
      "hasCurveFrom": true,
      "hasCurveTo": false,
      "point": "{1, 0.15921922890789181}"
    },
    {
      "_class": "curvePoint",
      "cornerRadius": 0,
      "curveFrom": "{0.50025316455692725, 0}",
      "curveMode": 4,
      "curveTo": "{0.77620253164556852, 0}",
      "hasCurveFrom": false,
      "hasCurveTo": true,
      "point": "{0.50025316455692725, 0}"
    }
  ],
  "resizingConstraint": 63,
  "resizingType": 0,
  "rotation": 0,
  "shouldBreakMaskChain": false
}