{
  "_class": "shapeGroup",
  "clippingMaskMode": 0,
  "do_objectID": "CDD17891-9267-4497-80BB-47C880FD1722",
  "exportOptions": {
    "_class": "exportOptions",
    "exportFormats": [
    ],
    "includedLayerIds": [
    ],
    "layerOptions": 0,
    "shouldTrim": false
  },
  "frame": {
    "_class": "rect",
    "constrainProportions": false,
    "height": 2,
    "width": 562,
    "x": 0,
    "y": 49
  },
  "hasClickThrough": false,
  "hasClippingMask": false,
  "isFlippedHorizontal": false,
  "isFlippedVertical": false,
  "isLocked": false,
  "isVisible": true,
  "layerListExpandedType": 0,
  "layers": [
    {
      "class": "shapePath",
      "id": "B440A6FE-BDF8-4FD6-BF5F-C7E8D61B9F10"
    }
  ],
  "name": "Axis",
  "nameIsFixed": true,
  "resizingConstraint": 58,
  "resizingType": 0,
  "rotation": 0,
  "shouldBreakMaskChain": false,
  "style": {
    "sharedObjectID": "7E19C0F9-EE31-4F7F-893D-9C1E029DBA81"
  },
  "userInfo": {
    "com.animaapp.stc-sketch-plugin": {
      "kModelPropertiesKey": {
      }
    }
  },
  "windingRule": 1
}