{
  "_class": "shapePath",
  "booleanOperation": 0,
  "do_objectID": "08E00C91-5BD1-4A3C-93E0-CE8711218E0D",
  "edited": true,
  "exportOptions": {
    "_class": "exportOptions",
    "exportFormats": [
    ],
    "includedLayerIds": [
    ],
    "layerOptions": 0,
    "shouldTrim": false
  },
  "frame": {
    "_class": "rect",
    "constrainProportions": false,
    "height": 12.80166147733661,
    "width": 17.95197681949377,
    "x": 17.97298696096526,
    "y": 0
  },
  "isClosed": true,
  "isFlippedHorizontal": false,
  "isFlippedVertical": false,
  "isLocked": false,
  "isVisible": true,
  "layerListExpandedType": 0,
  "name": "Fill 12",
  "nameIsFixed": false,
  "path": {
    "_class": "path",
    "isClosed": true,
    "pointRadiusBehaviour": 1,
    "points": [
      {
        "_class": "curvePoint",
        "cornerRadius": 0,
        "curveFrom": "{1, 0.54110698147833991}",
        "curveMode": 1,
        "curveTo": "{1, 0.54110698147833991}",
        "hasCurveFrom": false,
        "hasCurveTo": false,
        "point": "{1, 0.54110698147833991}"
      },
      {
        "_class": "curvePoint",
        "cornerRadius": 0,
        "curveFrom": "{0.41168162907816946, 0}",
        "curveMode": 1,
        "curveTo": "{0.41168162907816946, 0}",
        "hasCurveFrom": false,
        "hasCurveTo": false,
        "point": "{0.41168162907816946, 0}"
      },
      {
        "_class": "curvePoint",
        "cornerRadius": 0,
        "curveFrom": "{0, 0.48401523680273884}",
        "curveMode": 1,
        "curveTo": "{0, 0.48401523680273884}",
        "hasCurveFrom": false,
        "hasCurveTo": false,
        "point": "{0, 0.48401523680273884}"
      },
      {
        "_class": "curvePoint",
        "cornerRadius": 0,
        "curveFrom": "{0.59320122618786963, 1}",
        "curveMode": 1,
        "curveTo": "{0.59320122618786963, 1}",
        "hasCurveFrom": false,
        "hasCurveTo": false,
        "point": "{0.59320122618786963, 1}"
      }
    ]
  },
  "pointRadiusBehaviour": 1,
  "points": [
    {
      "_class": "curvePoint",
      "cornerRadius": 0,
      "curveFrom": "{1, 0.54110698147833991}",
      "curveMode": 1,
      "curveTo": "{1, 0.54110698147833991}",
      "hasCurveFrom": false,
      "hasCurveTo": false,
      "point": "{1, 0.54110698147833991}"
    },
    {
      "_class": "curvePoint",
      "cornerRadius": 0,
      "curveFrom": "{0.41168162907816946, 0}",
      "curveMode": 1,
      "curveTo": "{0.41168162907816946, 0}",
      "hasCurveFrom": false,
      "hasCurveTo": false,
      "point": "{0.41168162907816946, 0}"
    },
    {
      "_class": "curvePoint",
      "cornerRadius": 0,
      "curveFrom": "{0, 0.48401523680273884}",
      "curveMode": 1,
      "curveTo": "{0, 0.48401523680273884}",
      "hasCurveFrom": false,
      "hasCurveTo": false,
      "point": "{0, 0.48401523680273884}"
    },
    {
      "_class": "curvePoint",
      "cornerRadius": 0,
      "curveFrom": "{0.59320122618786963, 1}",
      "curveMode": 1,
      "curveTo": "{0.59320122618786963, 1}",
      "hasCurveFrom": false,
      "hasCurveTo": false,
      "point": "{0.59320122618786963, 1}"
    }
  ],
  "resizingConstraint": 63,
  "resizingType": 0,
  "rotation": 0,
  "shouldBreakMaskChain": false
}