{
  "_class": "shapeGroup",
  "clippingMaskMode": 0,
  "do_objectID": "86DFC73F-F00B-4E70-AFD7-F6643B38AAEB",
  "exportOptions": {
    "_class": "exportOptions",
    "exportFormats": [
    ],
    "includedLayerIds": [
    ],
    "layerOptions": 0,
    "shouldTrim": false
  },
  "frame": {
    "_class": "rect",
    "constrainProportions": false,
    "height": 134.3684210526317,
    "width": 70,
    "x": 0,
    "y": 23.81578947368416
  },
  "hasClickThrough": false,
  "hasClippingMask": false,
  "isFlippedHorizontal": false,
  "isFlippedVertical": false,
  "isLocked": false,
  "isVisible": true,
  "layerListExpandedType": 0,
  "layers": [
    {
      "class": "rectangle",
      "id": "57CFED67-0E30-4620-93A4-1F789ADA6AAF"
    }
  ],
  "name": "Shape",
  "nameIsFixed": true,
  "resizingConstraint": 63,
  "resizingType": 0,
  "rotation": 0,
  "shouldBreakMaskChain": false,
  "style": {
    "sharedObjectID": "29C97583-6C66-427A-A5DA-16D305B09330"
  },
  "userInfo": {
    "com.animaapp.stc-sketch-plugin": {
      "kModelPropertiesKey": {
      }
    }
  },
  "windingRule": 1
}