{
  "_class": "shapeGroup",
  "clippingMaskMode": 0,
  "do_objectID": "A36D0CB6-9B6D-43A7-BBFE-FB7A05E5C729",
  "exportOptions": {
    "_class": "exportOptions",
    "do_objectID": "01438190-2630-4B50-B638-26B3253A3B29",
    "exportFormats": [
    ],
    "includedLayerIds": [
    ],
    "layerOptions": 0,
    "shouldTrim": false
  },
  "frame": {
    "_class": "rect",
    "constrainProportions": false,
    "do_objectID": "E7E76446-05C4-4A5C-85FD-AFC31A92C134",
    "height": 49.68516949152539,
    "width": 49.04718650793652,
    "x": 57.57194444444432,
    "y": 0.07330508474576349
  },
  "hasClickThrough": false,
  "hasClippingMask": false,
  "isFlippedHorizontal": false,
  "isFlippedVertical": false,
  "isLocked": false,
  "isVisible": true,
  "layerListExpandedType": 1,
  "layers": [
    {
      "class": "shapePath",
      "id": "EEC62054-CB6A-41C2-AE85-631B7A003438"
    },
    {
      "class": "shapePath",
      "id": "3D03CE15-6FA4-44DC-9485-38666ED3321A"
    }
  ],
  "name": "Fill 3",
  "nameIsFixed": false,
  "resizingConstraint": 63,
  "resizingType": 0,
  "rotation": 0,
  "shouldBreakMaskChain": false,
  "style": {
    "_class": "style",
    "do_objectID": "7F7FBC03-DF9D-4BCF-A3E8-77CD1CE4E2BB",
    "endDecorationType": 0,
    "fills": [
      {
        "_class": "fill",
        "color": {
          "_class": "color",
          "alpha": 1,
          "blue": 0.03378957882523537,
          "green": 0.0419718399643898,
          "red": 0.03970737755298615
        },
        "fillType": 0,
        "isEnabled": true,
        "noiseIndex": 0,
        "noiseIntensity": 0,
        "patternFillType": 1,
        "patternTileScale": 1
      }
    ],
    "miterLimit": 10,
    "startDecorationType": 0
  },
  "windingRule": 1
}