{
  "_class": "shapePath",
  "booleanOperation": 3,
  "do_objectID": "0746605A-0A53-4351-B1C7-01F3162754E0",
  "edited": true,
  "exportOptions": {
    "_class": "exportOptions",
    "exportFormats": [
    ],
    "includedLayerIds": [
    ],
    "layerOptions": 0,
    "shouldTrim": false
  },
  "frame": {
    "_class": "rect",
    "constrainProportions": false,
    "height": 6.962699822380106,
    "width": 39.57597173144877,
    "x": 119.2226148409894,
    "y": 19.39609236234458
  },
  "isClosed": true,
  "isFlippedHorizontal": false,
  "isFlippedVertical": false,
  "isLocked": false,
  "isVisible": true,
  "layerListExpandedType": 0,
  "name": "Shape",
  "nameIsFixed": false,
  "path": {
    "_class": "path",
    "isClosed": true,
    "pointRadiusBehaviour": 1,
    "points": [
      {
        "_class": "curvePoint",
        "cornerRadius": 0,
        "curveFrom": "{0.087499999999999994, 0}",
        "curveMode": 4,
        "curveTo": "{0.039175084389805548, 0}",
        "hasCurveFrom": false,
        "hasCurveTo": true,
        "point": "{0.087499999999999994, 0}"
      },
      {
        "_class": "curvePoint",
        "cornerRadius": 0,
        "curveFrom": "{0.96082491561019412, 0}",
        "curveMode": 4,
        "curveTo": "{0.91249999999999998, 0}",
        "hasCurveFrom": true,
        "hasCurveTo": false,
        "point": "{0.91249999999999998, 0}"
      },
      {
        "_class": "curvePoint",
        "cornerRadius": 0,
        "curveFrom": "{1, 0.77614237491539428}",
        "curveMode": 2,
        "curveTo": "{1, 0.22385762508460516}",
        "hasCurveFrom": true,
        "hasCurveTo": true,
        "point": "{1, 0.5}"
      },
      {
        "_class": "curvePoint",
        "cornerRadius": 0,
        "curveFrom": "{0.91249999999999998, 1}",
        "curveMode": 4,
        "curveTo": "{0.96082491561019412, 1}",
        "hasCurveFrom": false,
        "hasCurveTo": true,
        "point": "{0.91249999999999998, 1}"
      },
      {
        "_class": "curvePoint",
        "cornerRadius": 0,
        "curveFrom": "{0.039175084389805548, 1}",
        "curveMode": 4,
        "curveTo": "{0.087499999999999994, 1}",
        "hasCurveFrom": true,
        "hasCurveTo": false,
        "point": "{0.087499999999999994, 1}"
      },
      {
        "_class": "curvePoint",
        "cornerRadius": 0,
        "curveFrom": "{0, 0.22385762508460263}",
        "curveMode": 2,
        "curveTo": "{0, 0.77614237491539739}",
        "hasCurveFrom": true,
        "hasCurveTo": true,
        "point": "{0, 0.5}"
      }
    ]
  },
  "pointRadiusBehaviour": 1,
  "points": [
    {
      "_class": "curvePoint",
      "cornerRadius": 0,
      "curveFrom": "{0.087499999999999994, 0}",
      "curveMode": 4,
      "curveTo": "{0.039175084389805548, 0}",
      "hasCurveFrom": false,
      "hasCurveTo": true,
      "point": "{0.087499999999999994, 0}"
    },
    {
      "_class": "curvePoint",
      "cornerRadius": 0,
      "curveFrom": "{0.96082491561019412, 0}",
      "curveMode": 4,
      "curveTo": "{0.91249999999999998, 0}",
      "hasCurveFrom": true,
      "hasCurveTo": false,
      "point": "{0.91249999999999998, 0}"
    },
    {
      "_class": "curvePoint",
      "cornerRadius": 0,
      "curveFrom": "{1, 0.77614237491539428}",
      "curveMode": 2,
      "curveTo": "{1, 0.22385762508460516}",
      "hasCurveFrom": true,
      "hasCurveTo": true,
      "point": "{1, 0.5}"
    },
    {
      "_class": "curvePoint",
      "cornerRadius": 0,
      "curveFrom": "{0.91249999999999998, 1}",
      "curveMode": 4,
      "curveTo": "{0.96082491561019412, 1}",
      "hasCurveFrom": false,
      "hasCurveTo": true,
      "point": "{0.91249999999999998, 1}"
    },
    {
      "_class": "curvePoint",
      "cornerRadius": 0,
      "curveFrom": "{0.039175084389805548, 1}",
      "curveMode": 4,
      "curveTo": "{0.087499999999999994, 1}",
      "hasCurveFrom": true,
      "hasCurveTo": false,
      "point": "{0.087499999999999994, 1}"
    },
    {
      "_class": "curvePoint",
      "cornerRadius": 0,
      "curveFrom": "{0, 0.22385762508460263}",
      "curveMode": 2,
      "curveTo": "{0, 0.77614237491539739}",
      "hasCurveFrom": true,
      "hasCurveTo": true,
      "point": "{0, 0.5}"
    }
  ],
  "resizingConstraint": 63,
  "resizingType": 0,
  "rotation": 0,
  "shouldBreakMaskChain": false
}