{
  "_class": "shapePath",
  "booleanOperation": -1,
  "do_objectID": "7DB9B99F-C62D-4073-BE50-3D1197FC75FB",
  "edited": true,
  "exportOptions": {
    "_class": "exportOptions",
    "exportFormats": [
    ],
    "includedLayerIds": [
    ],
    "layerOptions": 0,
    "shouldTrim": false
  },
  "frame": {
    "_class": "rect",
    "constrainProportions": false,
    "height": 9.625,
    "width": 6.875,
    "x": 12.375,
    "y": 2.75
  },
  "isClosed": true,
  "isFlippedHorizontal": false,
  "isFlippedVertical": false,
  "isLocked": false,
  "isVisible": true,
  "layerListExpandedType": 0,
  "name": "Path",
  "nameIsFixed": false,
  "path": {
    "_class": "path",
    "isClosed": true,
    "pointRadiusBehaviour": 0,
    "points": [
      {
        "_class": "curvePoint",
        "cornerRadius": 0,
        "curveFrom": "{0, 0.14285714285714285}",
        "curveMode": 1,
        "curveTo": "{0, 0.14285714285714285}",
        "hasCurveFrom": false,
        "hasCurveTo": false,
        "point": "{0, 0.14285714285714285}"
      },
      {
        "_class": "curvePoint",
        "cornerRadius": 0,
        "curveFrom": "{0, 0.93607142857142989}",
        "curveMode": 4,
        "curveTo": "{0, 0.8571428571428571}",
        "hasCurveFrom": true,
        "hasCurveTo": false,
        "point": "{0, 0.8571428571428571}"
      },
      {
        "_class": "curvePoint",
        "cornerRadius": 0,
        "curveFrom": "{0.20000000000000001, 1}",
        "curveMode": 4,
        "curveTo": "{0.089499999999999608, 1}",
        "hasCurveFrom": false,
        "hasCurveTo": true,
        "point": "{0.20000000000000001, 1}"
      },
      {
        "_class": "curvePoint",
        "cornerRadius": 0,
        "curveFrom": "{0.91050000000000042, 1}",
        "curveMode": 4,
        "curveTo": "{0.80000000000000004, 1}",
        "hasCurveFrom": true,
        "hasCurveTo": false,
        "point": "{0.80000000000000004, 1}"
      },
      {
        "_class": "curvePoint",
        "cornerRadius": 0,
        "curveFrom": "{1, 0.8571428571428571}",
        "curveMode": 4,
        "curveTo": "{1, 0.93607142857142989}",
        "hasCurveFrom": false,
        "hasCurveTo": true,
        "point": "{1, 0.8571428571428571}"
      },
      {
        "_class": "curvePoint",
        "cornerRadius": 0,
        "curveFrom": "{1, 0.063928571428570127}",
        "curveMode": 4,
        "curveTo": "{1, 0.14285714285714285}",
        "hasCurveFrom": true,
        "hasCurveTo": false,
        "point": "{1, 0.14285714285714285}"
      },
      {
        "_class": "curvePoint",
        "cornerRadius": 0,
        "curveFrom": "{0.80000000000000004, 0}",
        "curveMode": 4,
        "curveTo": "{0.91050000000000042, 0}",
        "hasCurveFrom": false,
        "hasCurveTo": true,
        "point": "{0.80000000000000004, 0}"
      },
      {
        "_class": "curvePoint",
        "cornerRadius": 0,
        "curveFrom": "{0.089499999999999608, 0}",
        "curveMode": 4,
        "curveTo": "{0.20000000000000001, 0}",
        "hasCurveFrom": true,
        "hasCurveTo": false,
        "point": "{0.20000000000000001, 0}"
      },
      {
        "_class": "curvePoint",
        "cornerRadius": 0,
        "curveFrom": "{0, 0.14285714285714285}",
        "curveMode": 4,
        "curveTo": "{0, 0.063928571428570127}",
        "hasCurveFrom": false,
        "hasCurveTo": true,
        "point": "{0, 0.14285714285714285}"
      }
    ]
  },
  "pointRadiusBehaviour": 0,
  "points": [
    {
      "_class": "curvePoint",
      "cornerRadius": 0,
      "curveFrom": "{0, 0.14285714285714285}",
      "curveMode": 1,
      "curveTo": "{0, 0.14285714285714285}",
      "hasCurveFrom": false,
      "hasCurveTo": false,
      "point": "{0, 0.14285714285714285}"
    },
    {
      "_class": "curvePoint",
      "cornerRadius": 0,
      "curveFrom": "{0, 0.93607142857142989}",
      "curveMode": 4,
      "curveTo": "{0, 0.8571428571428571}",
      "hasCurveFrom": true,
      "hasCurveTo": false,
      "point": "{0, 0.8571428571428571}"
    },
    {
      "_class": "curvePoint",
      "cornerRadius": 0,
      "curveFrom": "{0.20000000000000001, 1}",
      "curveMode": 4,
      "curveTo": "{0.089499999999999608, 1}",
      "hasCurveFrom": false,
      "hasCurveTo": true,
      "point": "{0.20000000000000001, 1}"
    },
    {
      "_class": "curvePoint",
      "cornerRadius": 0,
      "curveFrom": "{0.91050000000000042, 1}",
      "curveMode": 4,
      "curveTo": "{0.80000000000000004, 1}",
      "hasCurveFrom": true,
      "hasCurveTo": false,
      "point": "{0.80000000000000004, 1}"
    },
    {
      "_class": "curvePoint",
      "cornerRadius": 0,
      "curveFrom": "{1, 0.8571428571428571}",
      "curveMode": 4,
      "curveTo": "{1, 0.93607142857142989}",
      "hasCurveFrom": false,
      "hasCurveTo": true,
      "point": "{1, 0.8571428571428571}"
    },
    {
      "_class": "curvePoint",
      "cornerRadius": 0,
      "curveFrom": "{1, 0.063928571428570127}",
      "curveMode": 4,
      "curveTo": "{1, 0.14285714285714285}",
      "hasCurveFrom": true,
      "hasCurveTo": false,
      "point": "{1, 0.14285714285714285}"
    },
    {
      "_class": "curvePoint",
      "cornerRadius": 0,
      "curveFrom": "{0.80000000000000004, 0}",
      "curveMode": 4,
      "curveTo": "{0.91050000000000042, 0}",
      "hasCurveFrom": false,
      "hasCurveTo": true,
      "point": "{0.80000000000000004, 0}"
    },
    {
      "_class": "curvePoint",
      "cornerRadius": 0,
      "curveFrom": "{0.089499999999999608, 0}",
      "curveMode": 4,
      "curveTo": "{0.20000000000000001, 0}",
      "hasCurveFrom": true,
      "hasCurveTo": false,
      "point": "{0.20000000000000001, 0}"
    },
    {
      "_class": "curvePoint",
      "cornerRadius": 0,
      "curveFrom": "{0, 0.14285714285714285}",
      "curveMode": 4,
      "curveTo": "{0, 0.063928571428570127}",
      "hasCurveFrom": false,
      "hasCurveTo": true,
      "point": "{0, 0.14285714285714285}"
    }
  ],
  "resizingConstraint": 63,
  "resizingType": 0,
  "rotation": 0,
  "shouldBreakMaskChain": false
}