{
  "_class": "shapeGroup",
  "clippingMaskMode": 0,
  "do_objectID": "62279998-0C16-4FA5-824F-9B90C35B38BC",
  "exportOptions": {
    "_class": "exportOptions",
    "exportFormats": [
    ],
    "includedLayerIds": [
    ],
    "layerOptions": 0,
    "shouldTrim": false
  },
  "frame": {
    "_class": "rect",
    "constrainProportions": true,
    "height": 22,
    "width": 22,
    "x": 1,
    "y": 1
  },
  "hasClickThrough": false,
  "hasClippingMask": true,
  "isFlippedHorizontal": false,
  "isFlippedVertical": false,
  "isLocked": false,
  "isVisible": true,
  "layerListExpandedType": 0,
  "layers": [
    {
      "class": "shapePath",
      "id": "D2CE092E-831F-4FD2-B3AF-5F31B8CF112C"
    },
    {
      "class": "shapePath",
      "id": "7DB9B99F-C62D-4073-BE50-3D1197FC75FB"
    },
    {
      "class": "shapePath",
      "id": "BDFA9E9D-3286-4C6C-94B8-972E6D268341"
    }
  ],
  "name": "Trello",
  "nameIsFixed": true,
  "resizingConstraint": 63,
  "resizingType": 0,
  "rotation": 0,
  "shouldBreakMaskChain": false,
  "style": {
    "_class": "style",
    "blur": {
      "_class": "blur",
      "center": "{0.5, 0.5}",
      "isEnabled": false,
      "motionAngle": 0,
      "radius": 12.89950232887248,
      "type": 0
    },
    "endDecorationType": 0,
    "miterLimit": 10,
    "sharedObjectID": "8B48313C-D555-4464-AE64-1CEFCAECE891",
    "startDecorationType": 0
  },
  "windingRule": 1
}