{
  "_class": "group",
  "do_objectID": "3AA57692-EC54-4681-A2D3-A385FA464B2A",
  "exportOptions": {
    "_class": "exportOptions",
    "exportFormats": [
    ],
    "includedLayerIds": [
    ],
    "layerOptions": 0,
    "shouldTrim": false
  },
  "frame": {
    "_class": "rect",
    "constrainProportions": false,
    "height": 149,
    "width": 263,
    "x": 150,
    "y": 560
  },
  "hasClickThrough": false,
  "isFlippedHorizontal": false,
  "isFlippedVertical": false,
  "isLocked": false,
  "isVisible": true,
  "layerListExpandedType": 0,
  "layers": [
    {
      "class": "symbolInstance",
      "id": "49CB52D2-F4EF-49CB-86D0-6EB37C4329CD"
    },
    {
      "class": "text",
      "id": "1B0E8AFF-BE59-4FBB-A409-E1445A233700"
    },
    {
      "class": "symbolInstance",
      "id": "B653FDA4-5E7B-4558-BA61-11C976DBE57F"
    }
  ],
  "name": "Newsletter",
  "nameIsFixed": true,
  "resizingConstraint": 61,
  "resizingType": 0,
  "rotation": 0,
  "shouldBreakMaskChain": false,
  "style": {
    "_class": "style",
    "endDecorationType": 0,
    "miterLimit": 10,
    "startDecorationType": 0
  }
}